admin_pretty_gfk/__init__.py
admin_pretty_gfk/mixins.py
admin_pretty_gfk/widgets.py
admin_pretty_gfk/templates/widgets/foreign_key_content_id.html
admin_pretty_gfk-0.0.4.dist-info/LICENSE
admin_pretty_gfk-0.0.4.dist-info/METADATA
admin_pretty_gfk-0.0.4.dist-info/WHEEL
admin_pretty_gfk-0.0.4.dist-info/top_level.txt
admin_pretty_gfk-0.0.4.dist-info/RECORD
