Metadata-Version: 2.2
Name: admin_pretty_gfk
Version: 0.0.4
Summary: Custom Django admin mixin and widgets for handling generic foreign keys (GFKs) more intuitively.
Author-email: Andrii Tierzov <avtierzov@gmail.com>
License: MIT License
Project-URL: Homepage, https://github.com/DeDuHaNcHiK/admin-pretty-gfk
Classifier: Programming Language :: Python :: 3
Classifier: License :: OSI Approved :: MIT License
Classifier: Operating System :: OS Independent
Requires-Python: >=3.9
License-File: LICENSE
Requires-Dist: Django>=4.2.18
